<?xml version="1.0" encoding="UTF-8"?>
<PluginConfig>
    <Field id="showDebugInfo" type="checkbox" defaultValue="false">
        <Label>Enable debug logging</Label>
        <Description>Log all incoming Z-Wave bytes and cmd dict keys to Indigo log. Use this when first testing a new device.</Description>
    </Field>
    <Field id="logUnknownReports" type="checkbox" defaultValue="true">
        <Label>Log unknown command classes</Label>
        <Description>Store hex bytes of any unrecognised report in the rawLastReport state and write to Indigo log.</Description>
    </Field>

    <SeparatorLine/>

    <Field id="tempUnit" type="menu" defaultValue="degC">
        <Label>Temperature unit</Label>
        <Description>All temperature reports are converted to this unit before storing, regardless of what the sensor reports.</Description>
        <List>
            <Option value="degC">Celsius (degC)</Option>
            <Option value="degF">Fahrenheit (degF)</Option>
        </List>
    </Field>

    <SeparatorLine/>

    <Field id="enableStaleDetection" type="checkbox" defaultValue="true">
        <Label>Enable stale device detection</Label>
        <Description>Log a warning and mark deviceOnline=False if a device has not reported within the threshold below.</Description>
    </Field>
    <Field id="staleThresholdHours" type="menu" defaultValue="24">
        <Label>Stale threshold</Label>
        <Description>How long without any report before a device is considered offline. Battery devices report infrequently — allow extra margin.</Description>
        <List>
            <Option value="4">4 hours</Option>
            <Option value="8">8 hours</Option>
            <Option value="12">12 hours</Option>
            <Option value="24">24 hours</Option>
            <Option value="48">48 hours</Option>
            <Option value="72">72 hours</Option>
        </List>
    </Field>
</PluginConfig>
